xontrib/output_search.py
xontrib_output_search-0.6.5.dist-info/LICENSE
xontrib_output_search-0.6.5.dist-info/METADATA
xontrib_output_search-0.6.5.dist-info/WHEEL
xontrib_output_search-0.6.5.dist-info/top_level.txt
xontrib_output_search-0.6.5.dist-info/RECORD
