Metadata-Version: 2.1
Name: xontrib-output-search
Version: 0.6.5
Summary: Get identifiers, names, paths, URLs and words from the previous command output and use them for the next command in xonsh.
Home-page: https://github.com/anki-code/xontrib-output-search
Author: anki-code
Author-email: author@example.com
License: BSD
Project-URL: Documentation, https://github.com/anki-code/xontrib-output-search/blob/master/README.md
Project-URL: Code, https://github.com/anki-code/xontrib-output-search
Project-URL: Issue tracker, https://github.com/anki-code/xontrib-output-search/issues
Platform: any
Classifier: Environment :: Console
Classifier: Intended Audience :: End Users/Desktop
Classifier: Operating System :: OS Independent
Classifier: Programming Language :: Python
Classifier: Programming Language :: Unix Shell
Classifier: Topic :: System :: Shells
Classifier: Topic :: System :: System Shells
Classifier: Topic :: Terminals
Classifier: Topic :: System :: Networking
Classifier: License :: OSI Approved :: BSD License
Requires-Python: >=3.6
License-File: LICENSE
Requires-Dist: tokenize-output
